LICENSE
MANIFEST.in
README.md
requirements.txt
setup.py
rtrsub/__init__.py
rtrsub/rtrsub.py
rtrsub.egg-info/PKG-INFO
rtrsub.egg-info/SOURCES.txt
rtrsub.egg-info/dependency_links.txt
rtrsub.egg-info/entry_points.txt
rtrsub.egg-info/requires.txt
rtrsub.egg-info/top_level.txt