Metadata-Version: 2.1
Name: rtrsub
Version: 1.1.0
Summary: RTR Substitution
Home-page: https://github.com/job/rtrsub
Maintainer: Job Snijders
Maintainer-email: job@instituut.net
License: BSD 2-Clause
Keywords: rpki prefix routing networking
Platform: UNKNOWN
Classifier: Intended Audience :: Developers
Classifier: Topic :: Software Development :: Libraries :: Python Modules
Classifier: Topic :: System :: Networking
Classifier: License :: OSI Approved :: BSD License
Classifier: Programming Language :: Python :: 3 :: Only
License-File: LICENSE
